theia/__init__.py
theia/channels.py
theia/color.py
theia/flaticon.py
theia/gif.py
theia/grid.py
theia/image.py
theia/outline.py
theia/palettes.py
rafraser_theia-0.0.2.dist-info/LICENSE
rafraser_theia-0.0.2.dist-info/METADATA
rafraser_theia-0.0.2.dist-info/WHEEL
rafraser_theia-0.0.2.dist-info/top_level.txt
rafraser_theia-0.0.2.dist-info/RECORD
