Metadata-Version: 2.1
Name: rafraser-theia
Version: 0.0.2
Summary: Automating aspects of image generation
Home-page: https://github.com/rafraser/theia
Author: Robert A Fraser
Author-email: robert.fraser@uqconnect.edu.au
License: UNKNOWN
Platform: UNKNOWN
Classifier: Programming Language :: Python :: 3.8
Classifier: License :: OSI Approved :: MIT License
Classifier: Operating System :: OS Independent
Classifier: Development Status :: 2 - Pre-Alpha
Classifier: Natural Language :: English
Classifier: Topic :: Multimedia :: Graphics
Classifier: Typing :: Typed
Requires-Python: >=3.8
Requires-Dist: Pillow
Requires-Dist: requests
